permuto/__init__.py
permuto/cli.py
permuto/exceptions.py
permuto/permuto.py
permuto-0.1.0.dist-info/licenses/LICENSE
permuto-0.1.0.dist-info/METADATA
permuto-0.1.0.dist-info/WHEEL
permuto-0.1.0.dist-info/entry_points.txt
permuto-0.1.0.dist-info/top_level.txt
permuto-0.1.0.dist-info/RECORD
