Metadata-Version: 2.4
Name: permuto
Version: 0.1.0
Summary: Lightweight JSON templating engine with variable substitution and reverse mapping.
Author-email: Harri Pehkonen <harry.pehkonen@gmail.com>
License: This is free and unencumbered software released into the public domain.
Project-URL: Homepage, https://github.com/HarryPehkonen/PermutoPy
Project-URL: Bug Tracker, https://github.com/HarryPehkonen/PermutoPy/issues
Classifier: Programming Language :: Python :: 3
Classifier: License :: CC0 1.0 Universal (CC0 1.0) Public Domain Dedication
Classifier: Operating System :: OS Independent
Classifier: Topic :: Software Development :: Libraries :: Python Modules
Classifier: Topic :: Text Processing
Classifier: Intended Audience :: Developers
Requires-Python: >=3.7
License-File: LICENSE
Requires-Dist: jsonpointer>=2.0
Provides-Extra: test
Requires-Dist: pytest>=6.0; extra == "test"
Dynamic: license-file
